presencestats.py
pypresence_stats-2.dist-info/METADATA
pypresence_stats-2.dist-info/WHEEL
pypresence_stats-2.dist-info/entry_points.txt
pypresence_stats-2.dist-info/top_level.txt
pypresence_stats-2.dist-info/RECORD
