Metadata-Version: 2.1
Name: pypresence-stats
Version: 2
Summary: Presence-stats but you can make python script and launch it.
Home-page: https://redirect.rukchadisa.live/7SoIfy9ZMa
Author: Rukchad Wongprayoon
Author-email: contact@biomooping.tk
License: MIT
Keywords: Tools
Platform: UNKNOWN
Requires-Dist: pypresence
Requires-Dist: psutil
